pyd3tn/__init__.py
pyd3tn/bundle6.py
pyd3tn/bundle7.py
pyd3tn/crc.py
pyd3tn/eid.py
pyd3tn/helpers.py
pyd3tn/mtcp.py
pyd3tn/sdnv.py
pyd3tn/spp.py
pyd3tn/tcpcl.py
pyd3tn-0.14.5.dist-info/licenses/LICENSE
pyd3tn-0.14.5.dist-info/METADATA
pyd3tn-0.14.5.dist-info/WHEEL
pyd3tn-0.14.5.dist-info/top_level.txt
pyd3tn-0.14.5.dist-info/RECORD
