Metadata-Version: 2.4
Name: pyD3TN
Version: 0.14.5
Summary: Collection of DTN protocol implementations
Author-email: D3TN GmbH <contact@d3tn.com>
License: BSD-3-Clause OR Apache-2.0
Project-URL: Repository, https://gitlab.com/d3tn/ud3tn
Requires-Python: >=3.9
License-File: LICENSE
Requires-Dist: cbor2==5.6.5
Dynamic: license-file
